pid/__init__.py
pid/pid.py
pid_regulator-1.1.0.dist-info/LICENSE
pid_regulator-1.1.0.dist-info/METADATA
pid_regulator-1.1.0.dist-info/WHEEL
pid_regulator-1.1.0.dist-info/top_level.txt
pid_regulator-1.1.0.dist-info/RECORD
